odoo9_addon_partner_event-9.0.1.0.0-py2.7-nspkg.pth
odoo_addons/partner_event/__openerp__.py
odoo_addons/partner_event/__init__.py
odoo_addons/partner_event/README.rst
odoo_addons/partner_event/models/event_event.py
odoo_addons/partner_event/models/event_registration.py
odoo_addons/partner_event/models/res_partner.py
odoo_addons/partner_event/models/__init__.py
odoo_addons/partner_event/i18n/es.po
odoo_addons/partner_event/i18n/sl.po
odoo_addons/partner_event/wizard/res_partner_register_event_view.xml
odoo_addons/partner_event/wizard/__init__.py
odoo_addons/partner_event/wizard/res_partner_register_event.py
odoo_addons/partner_event/views/event_event_view.xml
odoo_addons/partner_event/views/event_registration_view.xml
odoo_addons/partner_event/views/res_partner_view.xml
odoo_addons/partner_event/tests/test_event_registration.py
odoo_addons/partner_event/tests/__init__.py
odoo_addons/partner_event/static/description/icon.png
odoo9_addon_partner_event-9.0.1.0.0.dist-info/top_level.txt
odoo9_addon_partner_event-9.0.1.0.0.dist-info/WHEEL
odoo9_addon_partner_event-9.0.1.0.0.dist-info/RECORD
odoo9_addon_partner_event-9.0.1.0.0.dist-info/metadata.json
odoo9_addon_partner_event-9.0.1.0.0.dist-info/DESCRIPTION.rst
odoo9_addon_partner_event-9.0.1.0.0.dist-info/METADATA
odoo9_addon_partner_event-9.0.1.0.0.dist-info/namespace_packages.txt
