Metadata-Version: 2.0
Name: odoo9-addon-partner-event
Version: 9.0.1.0.0
Summary: Link partner to events
Home-page: http://www.tecnativa.com
Author: Tecnativa,Odoo Community Association (OCA)
Author-email: support@odoo-community.org
License: UNKNOWN
Platform: UNKNOWN
Requires-Dist: odoo (<9.1a,>=9.0a)
Classifier: Programming Language :: Python :: 2.7
Classifier: Framework :: Odoo
